pysui/__init__.py
pysui/version.py
pysui/abstracts/__init__.py
pysui/abstracts/client_config.py
pysui/abstracts/client_keypair.py
pysui/abstracts/client_rpc.py
pysui/abstracts/client_types.py
pysui/sui/__init__.py
pysui/sui/sui_apidesc.py
pysui/sui/sui_bcsl.py
pysui/sui/sui_config.py
pysui/sui/sui_constants.py
pysui/sui/sui_crypto.py
pysui/sui/sui_excepts.py
pysui/sui/sui_txn_validator.py
pysui/sui/sui_utils.py
pysui/sui/sui_bcs/__init__.py
pysui/sui/sui_bcs/bcs.py
pysui/sui/sui_bcs/bcs_stnd.py
pysui/sui/sui_bcs/bcs_txne.py
pysui/sui/sui_bcs/pysui_bcs.py
pysui/sui/sui_builders/__init__.py
pysui/sui/sui_builders/base_builder.py
pysui/sui/sui_builders/exec_builders.py
pysui/sui/sui_builders/get_builders.py
pysui/sui/sui_builders/subscription_builders.py
pysui/sui/sui_clients/__init__.py
pysui/sui/sui_clients/async_client.py
pysui/sui/sui_clients/common.py
pysui/sui/sui_clients/subscribe.py
pysui/sui/sui_clients/sync_client.py
pysui/sui/sui_common/__init__.py
pysui/sui/sui_common/async_funcs.py
pysui/sui/sui_common/bcs_ast.py
pysui/sui/sui_common/bcs_to_json.py
pysui/sui/sui_common/client.py
pysui/sui/sui_common/json_to_bcs.py
pysui/sui/sui_common/jtobcs_pre.py
pysui/sui/sui_common/jtobcs_spec.json
pysui/sui/sui_common/move_to_bcs.py
pysui/sui/sui_common/mtobcs_pre.py
pysui/sui/sui_common/mtobcs_types.py
pysui/sui/sui_common/trxn_base.py
pysui/sui/sui_common/txb_pure.py
pysui/sui/sui_common/txb_signing.py
pysui/sui/sui_common/validators.py
pysui/sui/sui_common/config/__init__.py
pysui/sui/sui_common/config/confgroup.py
pysui/sui/sui_common/config/conflegacy.py
pysui/sui/sui_common/config/confmodel.py
pysui/sui/sui_common/config/pysui_config.py
pysui/sui/sui_grpc/__init__.py
pysui/sui/sui_grpc/pgrpc_absreq.py
pysui/sui/sui_grpc/pgrpc_async_txn.py
pysui/sui/sui_grpc/pgrpc_clients.py
pysui/sui/sui_grpc/pgrpc_requests.py
pysui/sui/sui_grpc/pgrpc_txb_gas.py
pysui/sui/sui_grpc/pgrpc_txn_async_argb.py
pysui/sui/sui_grpc/pgrpc_utils.py
pysui/sui/sui_grpc/suimsgs/__init__.py
pysui-0.95.0.dist-info/licenses/LICENSE
pysui-0.95.0.dist-info/METADATA
pysui-0.95.0.dist-info/WHEEL
pysui-0.95.0.dist-info/entry_points.txt
pysui-0.95.0.dist-info/top_level.txt
pysui-0.95.0.dist-info/RECORD
