Metadata-Version: 2.4
Name: pysui
Version: 0.95.0
Summary: SUI client Python SDK
License-Expression: Apache-2.0
Project-URL: changelog, https://github.com/FrankC01/pysui/blob/main/CHANGELOG.md
Project-URL: repository, https://github.com/FrankC01/pysui
Project-URL: issues, https://github.com/FrankC01/pysui/issues
Project-URL: documentation, https://pysui.readthedocs.io
Keywords: software development kit,sui,blockchain
Classifier: Development Status :: 4 - Beta
Classifier: Intended Audience :: Developers
Classifier: Topic :: Software Development
Classifier: Topic :: Software Development :: Libraries
Classifier: Programming Language :: Python
Classifier: Operating System :: OS Independent
Classifier: Programming Language :: Python :: 3.10
Classifier: Programming Language :: Python :: 3.11
Classifier: Programming Language :: Python :: 3.12
Classifier: Programming Language :: Python :: 3.13
Classifier: Programming Language :: Python :: 3 :: Only
Requires-Python: >=3.10
License-File: LICENSE
Requires-Dist: betterproto2[grpclib]<1.0.0,>=0.9.0
Requires-Dist: dataclasses_json<0.7.0,>=0.6.6
Requires-Dist: PyYAML<6.2,>=6.0.1
Requires-Dist: httpx<0.29,>=0.28.1
Requires-Dist: h2<5.0,>=4.2.0
Requires-Dist: jsonschema<4.30,>=4.23.0
Requires-Dist: websockets<16.0.0,>=15.0.1
Requires-Dist: gql[httpx,websockets]>=4.0.0
Requires-Dist: typing_utils<0.2.0,>=0.1.0
Requires-Dist: canoser==0.8.2
Requires-Dist: base58<2.2.0,>=2.1.1
Requires-Dist: Deprecated<1.3.0,>=1.2.14
Requires-Dist: pysui-fastcrypto>=0.7.0
Dynamic: license-file
